{
  "color-primary-100": "#EFFBEE",
  "color-primary-200": "#DEF7DE",
  "color-primary-300": "#C4E7C8",
  "color-primary-400": "#A9D0B1",
  "color-primary-500": "#85B293",
  "color-primary-600": "#619978",
  "color-primary-700": "#438062",
  "color-primary-800": "#2A674F",
  "color-primary-900": "#195543",
  "color-success-100": "#D9FCD4",
  "color-success-200": "#ABFAAB",
  "color-success-300": "#7FF289",
  "color-success-400": "#5DE676",
  "color-success-500": "#2CD65C",
  "color-success-600": "#20B859",
  "color-success-700": "#169A55",
  "color-success-800": "#0E7C4D",
  "color-success-900": "#086647",
  "color-info-100": "#D5F7FE",
  "color-info-200": "#ABEAFE",
  "color-info-300": "#82D8FE",
  "color-info-400": "#62C6FD",
  "color-info-500": "#2FA7FC",
  "color-info-600": "#2282D8",
  "color-info-700": "#1761B5",
  "color-info-800": "#0E4592",
  "color-info-900": "#093078",
  "color-warning-100": "#FFFCCF",
  "color-warning-200": "#FFF89F",
  "color-warning-300": "#FFF36F",
  "color-warning-400": "#FFEE4B",
  "color-warning-500": "#FFE70F",
  "color-warning-600": "#DBC40A",
  "color-warning-700": "#B7A207",
  "color-warning-800": "#938104",
  "color-warning-900": "#7A6902",
  "color-danger-100": "#FFE7DA",
  "color-danger-200": "#FFCAB5",
  "color-danger-300": "#FFA690",
  "color-danger-400": "#FF8575",
  "color-danger-500": "#FF4D47",
  "color-danger-600": "#DB333C",
  "color-danger-700": "#B72338",
  "color-danger-800": "#931632",
  "color-danger-900": "#7A0D2E"
}
